libertywrapper/__init__.py
libertywrapper/activity.py
libertywrapper/bot.py
libertywrapper/data.py
libertywrapper/faction.py
libertywrapper/fetcher.py
libertywrapper/game.py
libertywrapper/general.py
libertywrapper/player.py
libertywrapper/staff.py
libertywrapper/user.py
LibertyWrapper.py-0.1.dist-info/LICENSE
LibertyWrapper.py-0.1.dist-info/METADATA
LibertyWrapper.py-0.1.dist-info/WHEEL
LibertyWrapper.py-0.1.dist-info/top_level.txt
LibertyWrapper.py-0.1.dist-info/RECORD
